myprimelib99/__init__.py
myprimelib99/prime_numbers.py
myprimelib99/prime_numbersNew.py
myprimelib99-0.2.0.dist-info/LICENSE
myprimelib99-0.2.0.dist-info/METADATA
myprimelib99-0.2.0.dist-info/WHEEL
myprimelib99-0.2.0.dist-info/top_level.txt
myprimelib99-0.2.0.dist-info/RECORD
