Metadata-Version: 2.1
Name: myprimelib99
Version: 0.2.0
Summary: Create A small package to work with prime numbers
Author: spacenet2300
Author-email: endersu@outlook.com
Classifier: Programming Language :: Python :: 3
Classifier: License :: OSI Approved :: MIT License
Classifier: Operating System :: OS Independent
License-File: LICENSE
